uzpy/__version__.py
uzpy-1.3.0.dist-info/METADATA
uzpy-1.3.0.dist-info/WHEEL
uzpy-1.3.0.dist-info/entry_points.txt
uzpy-1.3.0.dist-info/licenses/LICENSE
uzpy-1.3.0.dist-info/RECORD
