Metadata-Version: 2.4
Name: uzpy
Version: 1.3.0
Summary: A tool to track where Python constructs are used and update docstrings
Project-URL: Documentation, https://github.com/twardoch/uzpy#readme
Project-URL: Issues, https://github.com/twardoch/uzpy/issues
Project-URL: Source, https://github.com/twardoch/uzpy
Author-email: Adam Twardoch <adam+github@twardoch.com>
License: MIT
License-File: LICENSE
Keywords: ast,code-analysis,docstrings,documentation,tree-sitter,usage-tracking
Classifier: Development Status :: 4 - Beta
Classifier: Intended Audience :: Developers
Classifier: License :: OSI Approved :: MIT License
Classifier: Operating System :: OS Independent
Classifier: Programming Language :: Python
Classifier: Programming Language :: Python :: 3.10
Classifier: Programming Language :: Python :: 3.11
Classifier: Programming Language :: Python :: 3.12
Classifier: Programming Language :: Python :: Implementation :: CPython
Classifier: Programming Language :: Python :: Implementation :: PyPy
Requires-Python: >=3.10
Requires-Dist: fire>=0.5.0
Requires-Dist: jedi>=0.19.0
Requires-Dist: libcst>=1.0.0
Requires-Dist: loguru>=0.7.0
Requires-Dist: pathspec>=0.11.0
Requires-Dist: rich>=13.0.0
Requires-Dist: rope>=1.7.0
Requires-Dist: tree-sitter-python>=0.20.0
Requires-Dist: tree-sitter>=0.20.0
Provides-Extra: all
Requires-Dist: absolufy-imports>=0.3.1; extra == 'all'
Requires-Dist: autoflake>=2.0.0; extra == 'all'
Requires-Dist: coverage[toml]>=7.6.12; extra == 'all'
Requires-Dist: isort>=6.0.1; extra == 'all'
Requires-Dist: mypy>=1.15.0; extra == 'all'
Requires-Dist: myst-parser>=3.0.0; extra == 'all'
Requires-Dist: pre-commit>=4.1.0; extra == 'all'
Requires-Dist: pytest-asyncio>=0.25.3; extra == 'all'
Requires-Dist: pytest-benchmark[histogram]>=5.1.0; extra == 'all'
Requires-Dist: pytest-cov>=6.0.0; extra == 'all'
Requires-Dist: pytest-xdist>=3.6.1; extra == 'all'
Requires-Dist: pytest>=8.3.4; extra == 'all'
Requires-Dist: pyupgrade>=3.19.1; extra == 'all'
Requires-Dist: ruff>=0.9.7; extra == 'all'
Requires-Dist: sphinx-autodoc-typehints>=2.0.0; extra == 'all'
Requires-Dist: sphinx-rtd-theme>=2.0.0; extra == 'all'
Requires-Dist: sphinx>=7.2.6; extra == 'all'
Provides-Extra: dev
Requires-Dist: absolufy-imports>=0.3.1; extra == 'dev'
Requires-Dist: autoflake>=2.0.0; extra == 'dev'
Requires-Dist: isort>=6.0.1; extra == 'dev'
Requires-Dist: mypy>=1.15.0; extra == 'dev'
Requires-Dist: pre-commit>=4.1.0; extra == 'dev'
Requires-Dist: pyupgrade>=3.19.1; extra == 'dev'
Requires-Dist: ruff>=0.9.7; extra == 'dev'
Provides-Extra: docs
Requires-Dist: myst-parser>=3.0.0; extra == 'docs'
Requires-Dist: sphinx-autodoc-typehints>=2.0.0; extra == 'docs'
Requires-Dist: sphinx-rtd-theme>=2.0.0; extra == 'docs'
Requires-Dist: sphinx>=7.2.6; extra == 'docs'
Provides-Extra: test
Requires-Dist: coverage[toml]>=7.6.12; extra == 'test'
Requires-Dist: pytest-asyncio>=0.25.3; extra == 'test'
Requires-Dist: pytest-benchmark[histogram]>=5.1.0; extra == 'test'
Requires-Dist: pytest-cov>=6.0.0; extra == 'test'
Requires-Dist: pytest-xdist>=3.6.1; extra == 'test'
Requires-Dist: pytest>=8.3.4; extra == 'test'
